piprints/Makefile
piprints/__init__.py
piprints/backup.sh
piprints/clear_database.sh
piprints/design/alert.xcf
piprints/design/error.xcf
piprints/design/info.xcf
piprints/design/ok.xcf
piprints/import_set_passwords.sh
piprints/import_sync_timestamps.sh
piprints/initial_import_messages.txt
piprints/main/__init__.py
piprints/main/admin.py
piprints/main/api_serializers.py
piprints/main/api_views.py
piprints/main/auth.py
piprints/main/data_import.py
piprints/main/excel.py
piprints/main/feeds.py
piprints/main/forms.py
piprints/main/google.py
piprints/main/management/__init__.py
piprints/main/management/commands/__init__.py
piprints/main/management/commands/google.py
piprints/main/management/commands/install.py
piprints/main/management/commands/merge_duplicates.py
piprints/main/management/commands/send_bulletin.py
piprints/main/management/commands/test.py
piprints/main/management/commands/wait_for_db.py
piprints/main/migrations/0001_initial.py
piprints/main/migrations/0002_auto_20160108_0818.py
piprints/main/migrations/0003_auto_20160121_1738.py
piprints/main/migrations/0004_researchproject_order.py
piprints/main/migrations/0005_auto_20160123_1228.py
piprints/main/migrations/0006_auto_20160124_1212.py
piprints/main/migrations/0007_populate_site_parameters.py
piprints/main/migrations/0008_auto_20160124_1803.py
piprints/main/migrations/0009_auto_20160124_2031.py
piprints/main/migrations/0010_siteparameters_welcome_message.py
piprints/main/migrations/0011_siteparameters_credits.py
piprints/main/migrations/0012_auto_20170428_1732.py
piprints/main/migrations/0013_auto_20170428_2243.py
piprints/main/migrations/0014_auto_20170428_2246.py
piprints/main/migrations/0015_seminar_google_id.py
piprints/main/migrations/0016_paper_arxiv_id.py
piprints/main/migrations/0017_auto_20170503_0016.py
piprints/main/migrations/0018_auto_20170520_1002.py
piprints/main/migrations/0019_person_orcid_id.py
piprints/main/migrations/0020_auto_20170530_1020.py
piprints-4.0.16.dist-info/METADATA
piprints-4.0.16.dist-info/WHEEL
piprints-4.0.16.dist-info/entry_points.txt
piprints-4.0.16.dist-info/RECORD
