Metadata-Version: 2.3
Name: piprints
Version: 4.0.16
Summary: preprint server
Author: Emanuele Paolini
Author-email: emanuele.paolini@gmail.com
Requires-Python: >=3.9.2
Classifier: Programming Language :: Python :: 3
Classifier: Programming Language :: Python :: 3.10
Classifier: Programming Language :: Python :: 3.11
Classifier: Programming Language :: Python :: 3.12
Classifier: Programming Language :: Python :: 3.13
Requires-Dist: argon2 (>=0.1.10,<0.2.0)
Requires-Dist: argon2-cffi (>=23.1.0,<24.0.0)
Requires-Dist: django (>=4.2.19)
Requires-Dist: django-filter (>=25.1,<26.0)
Requires-Dist: djangorestframework (>=3.15.2,<4.0.0)
Requires-Dist: jinja2 (>=3.1.5,<4.0.0)
Requires-Dist: pillow (>=11.1.0,<12.0.0)
Requires-Dist: python-dateutil (>=2.9.0.post0,<3.0.0)
Requires-Dist: python-dotenv (>=1.0.1,<2.0.0)
Requires-Dist: requests (>=2.32.3,<3.0.0)
